critical_node/APPLY/Fast_Validation_Model.py
critical_node/APPLY/Simulated_Reality.py
critical_node/APPLY/__init__.py
critical_node/COMMON/Get_Network_Attributes.py
critical_node/COMMON/Get_Node_Attributes.py
critical_node/COMMON/Graph.py
critical_node/COMMON/Read.py
critical_node/COMMON/Save.py
critical_node/COMMON/__init__.py
critical_node/DATA/Get_Data.py
critical_node/DATA/Inlay.py
critical_node/DATA/__init__.py
critical_node/DRAW/Brief.py
critical_node/DRAW/__init__.py
critical_node/EXPERIMENTAL/Accuracy.py
critical_node/EXPERIMENTAL/Monotonicity.py
critical_node/EXPERIMENTAL/Similarity.py
critical_node/EXPERIMENTAL/__init__.py
critical_node/MODEL/Basic_Model.py
critical_node/MODEL/Ks_Gravity_Model.py
critical_node/MODEL/Tra_Gravity_Model.py
critical_node/MODEL/__init__.py
critical_node-0.1.0.dist-info/LICENSE
critical_node-0.1.0.dist-info/METADATA
critical_node-0.1.0.dist-info/WHEEL
critical_node-0.1.0.dist-info/top_level.txt
critical_node-0.1.0.dist-info/RECORD
