Metadata-Version: 2.1
Name: critical_node
Version: 0.1.0
Summary: Used to identify key nodes for influential paper writing
Author-email: YunHengWang <1975667609@qq.com>
Project-URL: Homepage, https://github.com/pypa/sampleproject
Project-URL: Bug Tracker, https://github.com/pypa/sampleproject/issues
Classifier: Programming Language :: Python :: 3
Classifier: License :: OSI Approved :: MIT License
Classifier: Operating System :: OS Independent
Requires-Python: >=3.6
License-File: LICENSE
